README.txt
setup.py
docs/HISTORY.txt
docs/INSTALL.txt
docs/LICENSE.GPL
docs/LICENSE.txt
nmd/__init__.py
nmd.plonelinkasvideoembed.egg-info/PKG-INFO
nmd.plonelinkasvideoembed.egg-info/SOURCES.txt
nmd.plonelinkasvideoembed.egg-info/dependency_links.txt
nmd.plonelinkasvideoembed.egg-info/entry_points.txt
nmd.plonelinkasvideoembed.egg-info/namespace_packages.txt
nmd.plonelinkasvideoembed.egg-info/not-zip-safe
nmd.plonelinkasvideoembed.egg-info/requires.txt
nmd.plonelinkasvideoembed.egg-info/top_level.txt
nmd/plonelinkasvideoembed/__init__.py
nmd/plonelinkasvideoembed/configure.zcml
nmd/plonelinkasvideoembed/testifaces.py
nmd/plonelinkasvideoembed/tests.py
nmd/plonelinkasvideoembed/browser/__init__.py
nmd/plonelinkasvideoembed/browser/configure.zcml
nmd/plonelinkasvideoembed/browser/embed.pt
nmd/plonelinkasvideoembed/browser/link.py
nmd/plonelinkasvideoembed/profiles/default/metadata.xml
nmd/plonelinkasvideoembed/profiles/default/types.xml
nmd/plonelinkasvideoembed/profiles/default/types/Link.xml