Metadata-Version: 1.0
Name: nmd.plonelinkasvideoembed
Version: 0.6
Summary: Add a view plonelinkasvideoembed to display link content type as embed video by Makina Corpus
Home-page: http://svn.plone.org/svn/collective/nmd.plonelinkasvideoembed
Author: JeanMichel FRANCOIS
Author-email: jeanmichel.francois@makina-corpus.com
License: GPL
Platform: UNKNOWN
Classifier: Framework :: Plone
Classifier: Programming Language :: Python
Classifier: Topic :: Software Development :: Libraries :: Python Modules
